speedy_antlr_tool/__about__.py
speedy_antlr_tool/__init__.py
speedy_antlr_tool/extractor.py
speedy_antlr_tool/main.py
speedy_antlr_tool/objects.py
speedy_antlr_tool/validate.py
speedy_antlr_tool/templates/sa_X.pyt
speedy_antlr_tool/templates/sa_X_cpp_parser.cpp
speedy_antlr_tool/templates/sa_X_translator.cpp
speedy_antlr_tool/templates/sa_X_translator.h
speedy_antlr_tool/templates/speedy_antlr.cpp
speedy_antlr_tool/templates/speedy_antlr.h
speedy_antlr_tool-1.4.3.dist-info/LICENSE
speedy_antlr_tool-1.4.3.dist-info/METADATA
speedy_antlr_tool-1.4.3.dist-info/WHEEL
speedy_antlr_tool-1.4.3.dist-info/top_level.txt
speedy_antlr_tool-1.4.3.dist-info/RECORD
