Metadata-Version: 2.1
Name: speedy-antlr-tool
Version: 1.4.3
Summary: Generate an accelerator extension that makes your Antlr parser in Python super-fast!
Author: Alex Mykyta
License: BSD 3-Clause License
Project-URL: Source, https://github.com/amykyta3/speedy-antlr-tool
Project-URL: Tracker, https://github.com/amykyta3/speedy-antlr-tool/issues
Project-URL: Changelog, https://github.com/amykyta3/speedy-antlr-tool/releases
Project-URL: Documentation, http://speedy-antlr-tool.readthedocs.io
Classifier: Development Status :: 5 - Production/Stable
Classifier: Programming Language :: Python
Classifier: Programming Language :: Python :: 3
Classifier: Programming Language :: Python :: 3.6
Classifier: Programming Language :: Python :: 3.7
Classifier: Programming Language :: Python :: 3.8
Classifier: Programming Language :: Python :: 3.9
Classifier: Programming Language :: Python :: 3.10
Classifier: Programming Language :: Python :: 3.11
Classifier: Programming Language :: Python :: 3.12
Classifier: Programming Language :: Python :: 3 :: Only
Classifier: Intended Audience :: Developers
Classifier: License :: OSI Approved :: GNU General Public License v3 (GPLv3)
Classifier: Operating System :: OS Independent
Classifier: Topic :: Software Development :: Compilers
Classifier: Topic :: Software Development :: Code Generators
Requires-Python: >=3.6
License-File: LICENSE
Requires-Dist: antlr4-python3-runtime <4.14,>=4.10
Requires-Dist: jinja2
